pyuu/iter/__init__.py
pyuu/iter/bfs.py
pyuu/iter/common.py
pyuu/iter/dfs.py
pyuu/iter/tree_iter.py
pyuu.iter-0.0.1.dist-info/METADATA
pyuu.iter-0.0.1.dist-info/WHEEL
pyuu.iter-0.0.1.dist-info/top_level.txt
pyuu.iter-0.0.1.dist-info/RECORD
