Metadata-Version: 2.1
Name: pyuu.iter
Version: 0.0.1
Summary: A common library
Home-page: https://github.com/happyxianyu/uu
Author: happyxianyu
Author-email: happyxianyu623@outlook.com
License: Apache License 2.0
Platform: UNKNOWN
Requires-Python: >=3.8
